<?xml version="1.0" encoding="UTF-8" ?><escrutinio_sitio><num_a_elegir>49</num_a_elegir><nombre_lugar>Parlamento</nombre_lugar><nombre_disputado>escaños</nombre_disputado><porciento_escrutado>99.95</porciento_escrutado><nombre_sitio>Castilla La Mancha</nombre_sitio><ts>1306110099</ts><tipo_sitio>2</tipo_sitio><votos><contabilizados><cantidad>1188160</cantidad><porcentaje>76.92</porcentaje></contabilizados><abstenciones><cantidad>356439</cantidad><porcentaje>23.08</porcentaje></abstenciones><nulos><cantidad>15558</cantidad><porcentaje>1.31</porcentaje></nulos><blancos><cantidad>19625</cantidad><porcentaje>1.65</porcentaje></blancos></votos><resultados><numero_partidos>12</numero_partidos><partido><id_partido>3076</id_partido><nombre>PP</nombre><electos>25</electos><votos_numero>564335</votos_numero><votos_porciento>48.13</votos_porciento></partido><partido><id_partido>3186</id_partido><nombre>PSOE</nombre><electos>24</electos><votos_numero>508716</votos_numero><votos_porciento>43.38</votos_porciento></partido><partido><id_partido>2479</id_partido><nombre>IU</nombre><electos>0</electos><votos_numero>44208</votos_numero><votos_porciento>3.77</votos_porciento></partido><partido><id_partido>3780</id_partido><nombre>UPyD</nombre><electos>0</electos><votos_numero>20561</votos_numero><votos_porciento>1.75</votos_porciento></partido><partido><id_partido>2876</id_partido><nombre>PACMA</nombre><electos>0</electos><votos_numero>4092</votos_numero><votos_porciento>0.35</votos_porciento></partido><partido><id_partido>2891</id_partido><nombre>PCAS</nombre><electos>0</electos><votos_numero>2748</votos_numero><votos_porciento>0.23</votos_porciento></partido><partido><id_partido>2689</id_partido><nombre>LV-GV</nombre><electos>0</electos><votos_numero>2358</votos_numero><votos_porciento>0.2</votos_porciento></partido><partido><id_partido>1452</id_partido><nombre>ECOLO VERDES</nombre><electos>0</electos><votos_numero>1667</votos_numero><votos_porciento>0.14</votos_porciento></partido><partido><id_partido>1182</id_partido><nombre>CENB</nombre><electos>0</electos><votos_numero>1611</votos_numero><votos_porciento>0.14</votos_porciento></partido><partido><id_partido>3697</id_partido><nombre>U.C.I.T.</nombre><electos>0</electos><votos_numero>1426</votos_numero><votos_porciento>0.12</votos_porciento></partido><partido><id_partido>3625</id_partido><nombre>Ud.Ca</nombre><electos>0</electos><votos_numero>751</votos_numero><votos_porciento>0.06</votos_porciento></partido><partido><id_partido>1167</id_partido><nombre>CCD</nombre><electos>0</electos><votos_numero>504</votos_numero><votos_porciento>0.04</votos_porciento></partido></resultados></escrutinio_sitio>